<?xml version="1.0" ?>
<RegionData>
	<Airports>
		<Airport>
			<UniqueXMLID>26593</UniqueXMLID>
			<AirportName>Gautam Buddha Airport</AirportName>
			<AirportLevel>1</AirportLevel>
			<CityName>Bhairawa</CityName>
			<CountryName>Nepal</CountryName>
			<RegionName>Nepal</RegionName>
			<ICAOCode>VNBW</ICAOCode>
			<IATACode>BWA</IATACode>
			<Population>0</Population>
			<GateNumbers>1</GateNumbers>
			<HangarNumbers>1</HangarNumbers>
			<BuildingNumbers>1</BuildingNumbers>
			<BaseOrigin>1</BaseOrigin>
			<WealthRating>1</WealthRating>
			<Runways>
				<Runway>
					<Length>1510</Length>
					<SurfaceType>ASP</SurfaceType>
				</Runway>
			</Runways>
		</Airport>
		<Airport>
			<UniqueXMLID>26595</UniqueXMLID>
			<AirportName>Janakpur Airport</AirportName>
			<AirportLevel>1</AirportLevel>
			<CityName>Janakpur</CityName>
			<CountryName>Nepal</CountryName>
			<RegionName>Nepal</RegionName>
			<ICAOCode>VNJP</ICAOCode>
			<IATACode>JKR</IATACode>
			<Population>0</Population>
			<GateNumbers>1</GateNumbers>
			<HangarNumbers>1</HangarNumbers>
			<BuildingNumbers>1</BuildingNumbers>
			<BaseOrigin>1</BaseOrigin>
			<WealthRating>1</WealthRating>
			<Runways>
				<Runway>
					<Length>1006</Length>
					<SurfaceType>ASP</SurfaceType>
				</Runway>
			</Runways>
		</Airport>
		<Airport>
			<UniqueXMLID>26596</UniqueXMLID>
			<AirportName>Tribhuvan International Airport</AirportName>
			<AirportLevel>1</AirportLevel>
			<CityName>Kathmandu</CityName>
			<CountryName>Nepal</CountryName>
			<RegionName>Nepal</RegionName>
			<ICAOCode>VNKT</ICAOCode>
			<IATACode>KTM</IATACode>
			<Population>0</Population>
			<GateNumbers>1</GateNumbers>
			<HangarNumbers>1</HangarNumbers>
			<BuildingNumbers>1</BuildingNumbers>
			<BaseOrigin>1</BaseOrigin>
			<WealthRating>1</WealthRating>
			<Runways>
				<Runway>
					<Length>3050</Length>
					<SurfaceType>ASP</SurfaceType>
				</Runway>
			</Runways>
		</Airport>
		<Airport>
			<UniqueXMLID>26597</UniqueXMLID>
			<AirportName>Nepalgunj Airport</AirportName>
			<AirportLevel>1</AirportLevel>
			<CityName>Nepalgunj</CityName>
			<CountryName>Nepal</CountryName>
			<RegionName>Nepal</RegionName>
			<ICAOCode>VNNG</ICAOCode>
			<IATACode>KEP</IATACode>
			<Population>0</Population>
			<GateNumbers>1</GateNumbers>
			<HangarNumbers>1</HangarNumbers>
			<BuildingNumbers>1</BuildingNumbers>
			<BaseOrigin>1</BaseOrigin>
			<WealthRating>1</WealthRating>
			<Runways>
				<Runway>
					<Length>1504</Length>
					<SurfaceType>ASP</SurfaceType>
				</Runway>
			</Runways>
		</Airport>
		<Airport>
			<UniqueXMLID>26598</UniqueXMLID>
			<AirportName>Pokhara Airport</AirportName>
			<AirportLevel>1</AirportLevel>
			<CityName>Pokhara</CityName>
			<CountryName>Nepal</CountryName>
			<RegionName>Nepal</RegionName>
			<ICAOCode>VNPK</ICAOCode>
			<IATACode>PKR</IATACode>
			<Population>0</Population>
			<GateNumbers>1</GateNumbers>
			<HangarNumbers>1</HangarNumbers>
			<BuildingNumbers>1</BuildingNumbers>
			<BaseOrigin>1</BaseOrigin>
			<WealthRating>1</WealthRating>
			<Runways>
				<Runway>
					<Length>1439</Length>
					<SurfaceType>ASP</SurfaceType>
				</Runway>
			</Runways>
		</Airport>
		<Airport>
			<UniqueXMLID>308293</UniqueXMLID>
			<AirportName>Taplejung Airport</AirportName>
			<AirportLevel>1</AirportLevel>
			<CityName>Taplejung</CityName>
			<CountryName>Nepal</CountryName>
			<RegionName>Nepal</RegionName>
			<ICAOCode>VNTJ</ICAOCode>
			<IATACode>TPJ</IATACode>
			<Population>0</Population>
			<GateNumbers>1</GateNumbers>
			<HangarNumbers>1</HangarNumbers>
			<BuildingNumbers>1</BuildingNumbers>
			<BaseOrigin>1</BaseOrigin>
			<WealthRating>1</WealthRating>
			<Runways>
				<Runway>
					<Length>705</Length>
					<SurfaceType/>
				</Runway>
			</Runways>
		</Airport>
		<Airport>
			<UniqueXMLID>26600</UniqueXMLID>
			<AirportName>Biratnagar Airport</AirportName>
			<AirportLevel>1</AirportLevel>
			<CityName>Biratnagar</CityName>
			<CountryName>Nepal</CountryName>
			<RegionName>Nepal</RegionName>
			<ICAOCode>VNVT</ICAOCode>
			<IATACode>BIR</IATACode>
			<Population>0</Population>
			<GateNumbers>1</GateNumbers>
			<HangarNumbers>1</HangarNumbers>
			<BuildingNumbers>1</BuildingNumbers>
			<BaseOrigin>1</BaseOrigin>
			<WealthRating>1</WealthRating>
			<Runways>
				<Runway>
					<Length>1505</Length>
					<SurfaceType>ASP</SurfaceType>
				</Runway>
			</Runways>
		</Airport>
	</Airports>
	<RegionName>Nepal</RegionName>
</RegionData>
